{
  "board": {
    "kitchen": {
      "host": "192.168.0.121",
      "port": 8123,
      "debug": false,
      "collect": true
    },
    "radio": {
      "host": "192.168.0.21",
      "port": 9999,
      "debug": false,
      "collect": false
    },
    "dev": {
      "host": "192.168.0.120",
      "port": 8123,
      "debug": false,
      "collect": false
    }
  },
  "collector": {
    "host": "192.168.0.20",
    "port": 9000,
    "debug": false
  },
  "mqtt": {
    "host": "192.168.0.20",
    "port": 1883,
    "username": "mqtt",
    "password": "emkutete"
  }
}